sensirionbt
